<?xml version="1.0" encoding="UTF-8"?>
<qti-assessment-item
    xmlns="http://www.imsglobal.org/xsd/imsqtiasi_v3p0"
    xmlns:xsi="http://www.w3.org/2001/XMLSchema-instance"
    xsi:schemaLocation="http://www.imsglobal.org/xsd/imsqtiasi_v3p0 https://purl.imsglobal.org/spec/qti/v3p0/schema/xsd/imsqti_asiv3p0p1_v1p0.xsd http://www.w3.org/1998/Math/MathML https://purl.imsglobal.org/spec/mathml/v3p0/schema/xsd/mathml3.xsd"
    identifier="telling-time-analog-clock-hybrid"
    title="What time is it?"
    time-dependent="false"
    xml:lang="en-US">

    <qti-response-declaration identifier="RESPONSE_HR" cardinality="single" base-type="integer">
        <qti-correct-response>
            <qti-value>2</qti-value>
        </qti-correct-response>
    </qti-response-declaration>
    
    <qti-response-declaration identifier="RESPONSE_MIN" cardinality="single" base-type="integer">
        <qti-correct-response>
            <qti-value>5</qti-value>
        </qti-correct-response>
        <qti-mapping>
            <qti-map-entry map-key="05" mapped-value="5"/>
        </qti-mapping>
    </qti-response-declaration>

    <qti-outcome-declaration identifier="SCORE" cardinality="single" base-type="float">
        <qti-default-value>
            <qti-value>0</qti-value>
        </qti-default-value>
    </qti-outcome-declaration>
    <qti-outcome-declaration identifier="FEEDBACK" cardinality="single" base-type="identifier"/>

    <qti-item-body>
        <p>Look at the time on the clock.</p>
        <div id="reference_text">
            <img src="https://cdn.kastatic.org/ka-perseus-graphie/5d32e44363943ee9b3afd9d59814493febca6433.svg"
                 alt="An analog clock."
                 width="225"
                 height="225"/>
            <p><span class="qti-italic">Note: The shorter hour hand is just past the 2, and the longer minute hand is pointing directly at the 1.</span></p>
        </div>
        
        <qti-prompt>What time is it?</qti-prompt>
        <p>
            The time is <qti-text-entry-interaction response-identifier="RESPONSE_HR" expected-length="2"/> : <qti-text-entry-interaction response-identifier="RESPONSE_MIN" expected-length="2"/>.
        </p>

        <qti-feedback-block outcome-identifier="FEEDBACK" identifier="CORRECT" show-hide="show">
            <qti-content-body>
                <p><span class="qti-keyword-emphasis">Correct!</span> The time shown is 2:05.</p>
            </qti-content-body>
        </qti-feedback-block>
        <qti-feedback-block outcome-identifier="FEEDBACK" identifier="INCORRECT" show-hide="show">
            <qti-content-body>
                <p><span class="qti-keyword-emphasis">Not quite.</span> The hour hand is just past the 2, so the hour is 2. The minute hand pointing at the 1 represents 5 minutes past the hour. Therefore, the time is 2:05.</p>
            </qti-content-body>
        </qti-feedback-block>
    </qti-item-body>

    <qti-response-processing>
        <qti-response-condition>
            <qti-response-if>
                <qti-and>
                    <qti-match>
                        <qti-variable identifier="RESPONSE_HR"/>
                        <qti-correct identifier="RESPONSE_HR"/>
                    </qti-match>
                    <qti-match>
                        <qti-variable identifier="RESPONSE_MIN"/>
                        <qti-correct identifier="RESPONSE_MIN"/>
                    </qti-match>
                </qti-and>
                <qti-set-outcome-value identifier="SCORE">
                    <qti-base-value base-type="float">1</qti-base-value>
                </qti-set-outcome-value>
                <qti-set-outcome-value identifier="FEEDBACK">
                    <qti-base-value base-type="identifier">CORRECT</qti-base-value>
                </qti-set-outcome-value>
            </qti-response-if>
            <qti-response-else>
                <qti-set-outcome-value identifier="SCORE">
                    <qti-base-value base-type="float">0</qti-base-value>
                </qti-set-outcome-value>
                <qti-set-outcome-value identifier="FEEDBACK">
                    <qti-base-value base-type="identifier">INCORRECT</qti-base-value>
                </qti-set-outcome-value>
            </qti-response-else>
        </qti-response-condition>
    </qti-response-processing>

</qti-assessment-item>